README.txt
setup.py
docs/HISTORY.txt
docs/LICENSE.ZPL
plone/__init__.py
plone.postpublicationhook.egg-info/PKG-INFO
plone.postpublicationhook.egg-info/SOURCES.txt
plone.postpublicationhook.egg-info/dependency_links.txt
plone.postpublicationhook.egg-info/namespace_packages.txt
plone.postpublicationhook.egg-info/not-zip-safe
plone.postpublicationhook.egg-info/requires.txt
plone.postpublicationhook.egg-info/top_level.txt
plone/postpublicationhook/__init__.py
plone/postpublicationhook/configure.zcml
plone/postpublicationhook/event.py
plone/postpublicationhook/interfaces.py