Metadata-Version: 1.0
Name: plone.postpublicationhook
Version: 1.1
Summary: Zope 2 post-publication hook
Home-page: UNKNOWN
Author: Wichert Akkerman
Author-email: wichert@wiggy.net
License: ZPL
Platform: UNKNOWN
Classifier: Programming Language :: Python
Classifier: Environment :: Web Environment
Classifier: Framework :: Zope2
Classifier: Intended Audience :: Developers
Classifier: License :: OSI Approved :: Zope Public License
